alkuhlani_student/__init__.py
alkuhlani_student/__main__.py
alkuhlani_student/analyzer.py
alkuhlani_student-0.1.2.dist-info/licenses/LICENSE
alkuhlani_student-0.1.2.dist-info/METADATA
alkuhlani_student-0.1.2.dist-info/WHEEL
alkuhlani_student-0.1.2.dist-info/entry_points.txt
alkuhlani_student-0.1.2.dist-info/top_level.txt
alkuhlani_student-0.1.2.dist-info/RECORD
