Metadata-Version: 2.4
Name: alkuhlani-student
Version: 0.1.2
Summary: A simple Python package to analyze word frequency in text - محلل تكرار الكلمات
Home-page: https://github.com/alkuhlani/alkuhlani-student
Author: Alkuhlani Student (CYS 2)
Author-email: "Alkuhlani Student (CYS 2)" <alkuhlani@example.com>
License: MIT
Project-URL: Homepage, https://github.com/alkuhlani/alkuhlani-student
Project-URL: Bug Reports, https://github.com/alkuhlani/alkuhlani-student/issues
Project-URL: Source, https://github.com/alkuhlani/alkuhlani-student
Keywords: word,frequency,analysis,text,processing,nlp,arabic,alkuhlani,student
Classifier: Development Status :: 3 - Alpha
Classifier: Intended Audience :: Developers
Classifier: Intended Audience :: Education
Classifier: Topic :: Text Processing :: Linguistic
Classifier: License :: OSI Approved :: MIT License
Classifier: Programming Language :: Python :: 3
Classifier: Programming Language :: Python :: 3.7
Classifier: Programming Language :: Python :: 3.8
Classifier: Programming Language :: Python :: 3.9
Classifier: Programming Language :: Python :: 3.10
Classifier: Programming Language :: Python :: 3.11
Classifier: Natural Language :: Arabic
Classifier: Natural Language :: English
Requires-Python: >=3.7
License-File: LICENSE
Dynamic: author
Dynamic: home-page
Dynamic: license-file
Dynamic: requires-python
